{"is_past": true, "submissions": [{"1574": {"id": 579656, "date": 1590892466, "question_id": 1574, "submission_id": 75065180, "status": 10, "contest_id": 203, "data_region": "CN", "fail_count": 0}, "1575": {"id": 579782, "date": 1590892499, "question_id": 1575, "submission_id": 75065394, "status": 10, "contest_id": 203, "data_region": "CN", "fail_count": 0}, "1576": {"id": 581560, "date": 1590892812, "question_id": 1576, "submission_id": 75068328, "status": 10, "contest_id": 203, "data_region": "CN", "fail_count": 0}, "1577": {"id": 586592, "date": 1590894051, "question_id": 1577, "submission_id": 75079162, "status": 10, "contest_id": 203, "data_region": "CN", "fail_count": 0}}, {"1574": {"id": 579793, "date": 1590892501, "question_id": 1574, "submission_id": 75065409, "status": 10, "contest_id": 203, "data_region": "CN", "fail_count": 0}, "1575": {"id": 581278, "date": 1590892758, "question_id": 1575, "submission_id": 75067847, "status": 10, "contest_id": 203, "data_region": "CN", "fail_count": 0}, "1576": {"id": 582751, "date": 1590893100, "question_id": 1576, "submission_id": 75070616, "status": 10, "contest_id": 203, "data_region": "CN", "fail_count": 0}, "1577": {"id": 586624, "date": 1590894060, "question_id": 1577, "submission_id": 75079236, "status": 10, "contest_id": 203, "data_region": "CN", "fail_count": 0}}, {"1574": {"id": 580556, "date": 1590892645, "question_id": 1574, "submission_id": 75066687, "status": 10, "contest_id": 203, "data_region": "CN", "fail_count": 0}, "1575": {"id": 580596, "date": 1590892652, "question_id": 1575, "submission_id": 75066758, "status": 10, "contest_id": 203, "data_region": "CN", "fail_count": 0}, "1576": {"id": 581716, "date": 1590892849, "question_id": 1576, "submission_id": 75068622, "status": 10, "contest_id": 203, "data_region": "CN", "fail_count": 0}, "1577": {"id": 587022, "date": 1590894177, "question_id": 1577, "submission_id": 75080071, "status": 10, "contest_id": 203, "data_region": "CN", "fail_count": 0}}, {"1574": {"id": 579503, "date": 1590892399, "question_id": 1574, "submission_id": 75064873, "status": 10, "contest_id": 203, "data_region": "CN", "fail_count": 0}, "1575": {"id": 581246, "date": 1590892751, "question_id": 1575, "submission_id": 75067788, "status": 10, "contest_id": 203, "data_region": "CN", "fail_count": 0}, "1576": {"id": 581199, "date": 1590892745, "question_id": 1576, "submission_id": 75067718, "status": 10, "contest_id": 203, "data_region": "CN", "fail_count": 0}, "1577": {"id": 587125, "date": 1590894213, "question_id": 1577, "submission_id": 75080316, "status": 10, "contest_id": 203, "data_region": "CN", "fail_count": 0}}, {"1574": {"id": 581090, "date": 1590892725, "question_id": 1574, "submission_id": 75067547, "status": 10, "contest_id": 203, "data_region": "CN", "fail_count": 0}, "1575": {"id": 580858, "date": 1590892691, "question_id": 1575, "submission_id": 75067203, "status": 10, "contest_id": 203, "data_region": "CN", "fail_count": 1}, "1576": {"id": 580963, "date": 1590892708, "question_id": 1576, "submission_id": 75067365, "status": 10, "contest_id": 203, "data_region": "CN", "fail_count": 0}, "1577": {"id": 586445, "date": 1590894011, "question_id": 1577, "submission_id": 75078872, "status": 10, "contest_id": 203, "data_region": "CN", "fail_count": 0}}, {"1574": {"id": 579991, "date": 1590892554, "question_id": 1574, "submission_id": 75065749, "status": 10, "contest_id": 203, "data_region": "CN", "fail_count": 0}, "1575": {"id": 580472, "date": 1590892630, "question_id": 1575, "submission_id": 75066531, "status": 10, "contest_id": 203, "data_region": "CN", "fail_count": 0}, "1576": {"id": 581713, "date": 1590892848, "question_id": 1576, "submission_id": 75068613, "status": 10, "contest_id": 203, "data_region": "CN", "fail_count": 0}, "1577": {"id": 587647, "date": 1590894371, "question_id": 1577, "submission_id": 75081505, "status": 10, "contest_id": 203, "data_region": "CN", "fail_count": 0}}, {"1574": {"id": 579550, "date": 1590892428, "question_id": 1574, "submission_id": 75064992, "status": 10, "contest_id": 203, "data_region": "CN", "fail_count": 0}, "1575": {"id": 582192, "date": 1590892963, "question_id": 1575, "submission_id": 75069543, "status": 10, "contest_id": 203, "data_region": "CN", "fail_count": 0}, "1576": {"id": 583740, "date": 1590893329, "question_id": 1576, "submission_id": 75073222, "status": 10, "contest_id": 203, "data_region": "CN", "fail_count": 0}, "1577": {"id": 587824, "date": 1590894437, "question_id": 1577, "submission_id": 75082011, "status": 10, "contest_id": 203, "data_region": "CN", "fail_count": 0}}, {"1574": {"id": 581506, "date": 1590892799, "question_id": 1574, "submission_id": 75068230, "status": 10, "contest_id": 203, "data_region": "CN", "fail_count": 0}, "1575": {"id": 581740, "date": 1590892854, "question_id": 1575, "submission_id": 75068662, "status": 10, "contest_id": 203, "data_region": "CN", "fail_count": 0}, "1576": {"id": 581707, "date": 1590892846, "question_id": 1576, "submission_id": 75068601, "status": 10, "contest_id": 203, "data_region": "CN", "fail_count": 0}, "1577": {"id": 588482, "date": 1590894650, "question_id": 1577, "submission_id": 75083477, "status": 10, "contest_id": 203, "data_region": "CN", "fail_count": 0}}, {"1574": {"id": 579617, "date": 1590892450, "question_id": 1574, "submission_id": 75065099, "status": 10, "contest_id": 203, "data_region": "CN", "fail_count": 0}, "1575": {"id": 580445, "date": 1590892625, "question_id": 1575, "submission_id": 75066486, "status": 10, "contest_id": 203, "data_region": "CN", "fail_count": 0}, "1576": {"id": 580552, "date": 1590892644, "question_id": 1576, "submission_id": 75066681, "status": 10, "contest_id": 203, "data_region": "CN", "fail_count": 0}, "1577": {"id": 588626, "date": 1590894699, "question_id": 1577, "submission_id": 75083842, "status": 10, "contest_id": 203, "data_region": "CN", "fail_count": 0}}, {"1574": {"id": 580500, "date": 1590892634, "question_id": 1574, "submission_id": 75066581, "status": 10, "contest_id": 203, "data_region": "CN", "fail_count": 0}, "1575": {"id": 580994, "date": 1590892712, "question_id": 1575, "submission_id": 75067416, "status": 10, "contest_id": 203, "data_region": "CN", "fail_count": 0}, "1576": {"id": 582610, "date": 1590893066, "question_id": 1576, "submission_id": 75070363, "status": 10, "contest_id": 203, "data_region": "CN", "fail_count": 0}, "1577": {"id": 589024, "date": 1590894857, "question_id": 1577, "submission_id": 75084832, "status": 10, "contest_id": 203, "data_region": "CN", "fail_count": 0}}, {"1574": {"id": 580021, "date": 1590892560, "question_id": 1574, "submission_id": 75065796, "status": 10, "contest_id": 203, "data_region": "CN", "fail_count": 0}, "1575": {"id": 580969, "date": 1590892708, "question_id": 1575, "submission_id": 75067371, "status": 10, "contest_id": 203, "data_region": "CN", "fail_count": 1}, "1576": {"id": 581756, "date": 1590892858, "question_id": 1576, "submission_id": 75068695, "status": 10, "contest_id": 203, "data_region": "CN", "fail_count": 0}, "1577": {"id": 588787, "date": 1590894762, "question_id": 1577, "submission_id": 75084226, "status": 10, "contest_id": 203, "data_region": "CN", "fail_count": 0}}, {"1574": {"id": 580275, "date": 1590892604, "question_id": 1574, "submission_id": 75066216, "status": 10, "contest_id": 203, "data_region": "CN", "fail_count": 0}, "1575": {"id": 581129, "date": 1590892734, "question_id": 1575, "submission_id": 75067618, "status": 10, "contest_id": 203, "data_region": "CN", "fail_count": 0}, "1576": {"id": 583419, "date": 1590893255, "question_id": 1576, "submission_id": 75072607, "status": 10, "contest_id": 203, "data_region": "CN", "fail_count": 0}, "1577": {"id": 589529, "date": 1590895069, "question_id": 1577, "submission_id": 75086204, "status": 10, "contest_id": 203, "data_region": "CN", "fail_count": 0}}, {"1574": {"id": 580122, "date": 1590892582, "question_id": 1574, "submission_id": 75065983, "status": 10, "contest_id": 203, "data_region": "CN", "fail_count": 0}, "1575": {"id": 581835, "date": 1590892876, "question_id": 1575, "submission_id": 75068838, "status": 10, "contest_id": 203, "data_region": "CN", "fail_count": 1}, "1576": {"id": 583028, "date": 1590893164, "question_id": 1576, "submission_id": 75071529, "status": 10, "contest_id": 203, "data_region": "CN", "fail_count": 0}, "1577": {"id": 588820, "date": 1590894775, "question_id": 1577, "submission_id": 75084320, "status": 10, "contest_id": 203, "data_region": "CN", "fail_count": 0}}, {"1574": {"id": 581714, "date": 1590892848, "question_id": 1574, "submission_id": 75068615, "status": 10, "contest_id": 203, "data_region": "CN", "fail_count": 0}, "1575": {"id": 583651, "date": 1590893306, "question_id": 1575, "submission_id": 75073024, "status": 10, "contest_id": 203, "data_region": "CN", "fail_count": 1}, "1576": {"id": 581275, "date": 1590892757, "question_id": 1576, "submission_id": 75067842, "status": 10, "contest_id": 203, "data_region": "CN", "fail_count": 0}, "1577": {"id": 588832, "date": 1590894780, "question_id": 1577, "submission_id": 75084349, "status": 10, "contest_id": 203, "data_region": "CN", "fail_count": 0}}, {"1574": {"id": 580096, "date": 1590892577, "question_id": 1574, "submission_id": 75065935, "status": 10, "contest_id": 203, "data_region": "CN", "fail_count": 0}, "1575": {"id": 582197, "date": 1590892964, "question_id": 1575, "submission_id": 75069550, "status": 10, "contest_id": 203, "data_region": "CN", "fail_count": 1}, "1576": {"id": 583563, "date": 1590893286, "question_id": 1576, "submission_id": 75072867, "status": 10, "contest_id": 203, "data_region": "CN", "fail_count": 0}, "1577": {"id": 588876, "date": 1590894798, "question_id": 1577, "submission_id": 75084477, "status": 10, "contest_id": 203, "data_region": "CN", "fail_count": 0}}, {"1574": {"id": 579699, "date": 1590892476, "question_id": 1574, "submission_id": 75065245, "status": 10, "contest_id": 203, "data_region": "CN", "fail_count": 0}, "1575": {"id": 580843, "date": 1590892688, "question_id": 1575, "submission_id": 75067177, "status": 10, "contest_id": 203, "data_region": "CN", "fail_count": 1}, "1576": {"id": 581856, "date": 1590892882, "question_id": 1576, "submission_id": 75068885, "status": 10, "contest_id": 203, "data_region": "CN", "fail_count": 0}, "1577": {"id": 589037, "date": 1590894863, "question_id": 1577, "submission_id": 75084869, "status": 10, "contest_id": 203, "data_region": "CN", "fail_count": 0}}, {"1574": {"id": 583088, "date": 1590893178, "question_id": 1574, "submission_id": 75071996, "status": 10, "contest_id": 203, "data_region": "CN", "fail_count": 0}, "1575": {"id": 582706, "date": 1590893089, "question_id": 1575, "submission_id": 75070547, "status": 10, "contest_id": 203, "data_region": "CN", "fail_count": 0}, "1576": {"id": 581889, "date": 1590892889, "question_id": 1576, "submission_id": 75068944, "status": 10, "contest_id": 203, "data_region": "CN", "fail_count": 0}, "1577": {"id": 589883, "date": 1590895222, "question_id": 1577, "submission_id": 75087142, "status": 10, "contest_id": 203, "data_region": "CN", "fail_count": 0}}, {"1574": {"id": 579552, "date": 1590892429, "question_id": 1574, "submission_id": 75064994, "status": 10, "contest_id": 203, "data_region": "CN", "fail_count": 0}, "1575": {"id": 580236, "date": 1590892598, "question_id": 1575, "submission_id": 75066149, "status": 10, "contest_id": 203, "data_region": "CN", "fail_count": 0}, "1576": {"id": 582491, "date": 1590893038, "question_id": 1576, "submission_id": 75070127, "status": 10, "contest_id": 203, "data_region": "CN", "fail_count": 0}, "1577": {"id": 590270, "date": 1590895398, "question_id": 1577, "submission_id": 75088188, "status": 10, "contest_id": 203, "data_region": "CN", "fail_count": 0}}, {"1574": {"id": 581155, "date": 1590892737, "question_id": 1574, "submission_id": 75067655, "status": 10, "contest_id": 203, "data_region": "CN", "fail_count": 0}, "1575": {"id": 581681, "date": 1590892843, "question_id": 1575, "submission_id": 75068560, "status": 10, "contest_id": 203, "data_region": "CN", "fail_count": 0}, "1576": {"id": 584264, "date": 1590893461, "question_id": 1576, "submission_id": 75074263, "status": 10, "contest_id": 203, "data_region": "CN", "fail_count": 0}, "1577": {"id": 590422, "date": 1590895458, "question_id": 1577, "submission_id": 75088561, "status": 10, "contest_id": 203, "data_region": "CN", "fail_count": 0}}, {"1574": {"id": 579694, "date": 1590892475, "question_id": 1574, "submission_id": 75065236, "status": 10, "contest_id": 203, "data_region": "CN", "fail_count": 0}, "1575": {"id": 580710, "date": 1590892667, "question_id": 1575, "submission_id": 75066938, "status": 10, "contest_id": 203, "data_region": "CN", "fail_count": 1}, "1576": {"id": 581896, "date": 1590892891, "question_id": 1576, "submission_id": 75068956, "status": 10, "contest_id": 203, "data_region": "CN", "fail_count": 0}, "1577": {"id": 589053, "date": 1590894871, "question_id": 1577, "submission_id": 75084918, "status": 10, "contest_id": 203, "data_region": "CN", "fail_count": 1}}, {"1574": {"id": 579611, "date": 1590892449, "question_id": 1574, "submission_id": 75065090, "status": 10, "contest_id": 203, "data_region": "CN", "fail_count": 0}, "1575": {"id": 580023, "date": 1590892561, "question_id": 1575, "submission_id": 75065800, "status": 10, "contest_id": 203, "data_region": "CN", "fail_count": 0}, "1576": {"id": 581474, "date": 1590892793, "question_id": 1576, "submission_id": 75068183, "status": 10, "contest_id": 203, "data_region": "CN", "fail_count": 0}, "1577": {"id": 590595, "date": 1590895529, "question_id": 1577, "submission_id": 75089016, "status": 10, "contest_id": 203, "data_region": "CN", "fail_count": 0}}, {"1574": {"id": 579718, "date": 1590892480, "question_id": 1574, "submission_id": 75065276, "status": 10, "contest_id": 203, "data_region": "CN", "fail_count": 0}, "1575": {"id": 581686, "date": 1590892843, "question_id": 1575, "submission_id": 75068567, "status": 10, "contest_id": 203, "data_region": "CN", "fail_count": 0}, "1576": {"id": 584586, "date": 1590893536, "question_id": 1576, "submission_id": 75074853, "status": 10, "contest_id": 203, "data_region": "CN", "fail_count": 1}, "1577": {"id": 590375, "date": 1590895438, "question_id": 1577, "submission_id": 75088434, "status": 10, "contest_id": 203, "data_region": "CN", "fail_count": 0}}, {"1574": {"id": 580017, "date": 1590892560, "question_id": 1574, "submission_id": 75065792, "status": 10, "contest_id": 203, "data_region": "CN", "fail_count": 0}, "1575": {"id": 580281, "date": 1590892604, "question_id": 1575, "submission_id": 75066224, "status": 10, "contest_id": 203, "data_region": "CN", "fail_count": 0}, "1576": {"id": 582435, "date": 1590893023, "question_id": 1576, "submission_id": 75070019, "status": 10, "contest_id": 203, "data_region": "CN", "fail_count": 0}, "1577": {"id": 591179, "date": 1590895821, "question_id": 1577, "submission_id": 75090727, "status": 10, "contest_id": 203, "data_region": "CN", "fail_count": 0}}, {"1574": {"id": 579725, "date": 1590892482, "question_id": 1574, "submission_id": 75065289, "status": 10, "contest_id": 203, "data_region": "CN", "fail_count": 0}, "1575": {"id": 580568, "date": 1590892647, "question_id": 1575, "submission_id": 75066707, "status": 10, "contest_id": 203, "data_region": "CN", "fail_count": 0}, "1576": {"id": 582164, "date": 1590892958, "question_id": 1576, "submission_id": 75069502, "status": 10, "contest_id": 203, "data_region": "CN", "fail_count": 1}, "1577": {"id": 591013, "date": 1590895734, "question_id": 1577, "submission_id": 75090234, "status": 10, "contest_id": 203, "data_region": "CN", "fail_count": 0}}, {"1574": {"id": 580029, "date": 1590892562, "question_id": 1574, "submission_id": 75065809, "status": 10, "contest_id": 203, "data_region": "CN", "fail_count": 0}, "1575": {"id": 581523, "date": 1590892804, "question_id": 1575, "submission_id": 75068264, "status": 10, "contest_id": 203, "data_region": "CN", "fail_count": 0}, "1576": {"id": 583182, "date": 1590893203, "question_id": 1576, "submission_id": 75072175, "status": 10, "contest_id": 203, "data_region": "CN", "fail_count": 0}, "1577": {"id": 591528, "date": 1590896038, "question_id": 1577, "submission_id": 75091832, "status": 10, "contest_id": 203, "data_region": "CN", "fail_count": 0}}], "questions": [{"id": 1125, "question_id": 1574, "credit": 3, "title": "\u6570\u7ec4\u4e2d\u4e24\u5143\u7d20\u7684\u6700\u5927\u4e58\u79ef", "title_slug": "maximum-product-of-two-elements-in-an-array", "category_slug": "algorithms"}, {"id": 1126, "question_id": 1575, "credit": 4, "title": "\u5207\u5272\u540e\u9762\u79ef\u6700\u5927\u7684\u86cb\u7cd5", "title_slug": "maximum-area-of-a-piece-of-cake-after-horizontal-and-vertical-cuts", "category_slug": "algorithms"}, {"id": 1127, "question_id": 1576, "credit": 5, "title": "\u91cd\u65b0\u89c4\u5212\u8def\u7ebf", "title_slug": "reorder-routes-to-make-all-paths-lead-to-the-city-zero", "category_slug": "algorithms"}, {"id": 1128, "question_id": 1577, "credit": 7, "title": "\u4e24\u4e2a\u76d2\u5b50\u4e2d\u7403\u7684\u989c\u8272\u6570\u76f8\u540c\u7684\u6982\u7387", "title_slug": "probability-of-a-two-boxes-having-the-same-number-of-distinct-balls", "category_slug": "algorithms"}], "total_rank": [{"contest_id": 203, "username": "huangyuyang", "user_slug": "huangyuyang", "real_name": "ztxz16", "country_code": "CN", "country_name": "\u4e2d\u56fd", "rank": 0, "score": 19, "finish_time": 1590894051, "global_ranking": 0, "data_region": "CN"}, {"contest_id": 203, "username": "yang12138", "user_slug": "yang12138", "real_name": "yang12138", "country_code": "", "country_name": "", "rank": 1, "score": 19, "finish_time": 1590894060, "global_ranking": 0, "data_region": "CN"}, {"contest_id": 203, "username": "QingchuanZhang-Microsoft", "user_slug": "qingchuanzhang-microsoft", "real_name": "\u5f20\u6674\u5ddd", "country_code": "CN", "country_name": "\u4e2d\u56fd", "rank": 2, "score": 19, "finish_time": 1590894177, "global_ranking": 0, "data_region": "CN"}, {"contest_id": 203, "username": "Heltion", "user_slug": "heltion", "real_name": "\u4f55\u900a", "country_code": "CN", "country_name": "\u4e2d\u56fd", "rank": 3, "score": 19, "finish_time": 1590894213, "global_ranking": 0, "data_region": "CN"}, {"contest_id": 203, "username": "zerotrac2", "user_slug": "zerotrac2", "real_name": "zerotrac \ud83c\udf38", "country_code": "", "country_name": "\u6d77\u5916", "rank": 4, "score": 19, "finish_time": 1590894311, "global_ranking": 0, "data_region": "CN"}, {"contest_id": 203, "username": "zqy1018", "user_slug": "zqy1018", "real_name": "zqy1018", "country_code": "CN", "country_name": "\u4e2d\u56fd", "rank": 5, "score": 19, "finish_time": 1590894371, "global_ranking": 0, "data_region": "CN"}, {"contest_id": 203, "username": "arignote", "user_slug": "arignote", "real_name": "arignote", "country_code": "", "country_name": "", "rank": 6, "score": 19, "finish_time": 1590894437, "global_ranking": 0, "data_region": "CN"}, {"contest_id": 203, "username": "tian-tang-6", "user_slug": "tian-tang-6", "real_name": "\u5929\u5858", "country_code": "CN", "country_name": "\u4e2d\u56fd", "rank": 7, "score": 19, "finish_time": 1590894650, "global_ranking": 0, "data_region": "CN"}, {"contest_id": 203, "username": "laekov_prc", "user_slug": "laekov_prc", "real_name": "laekov", "country_code": "CN", "country_name": "\u4e2d\u56fd", "rank": 8, "score": 19, "finish_time": 1590894699, "global_ranking": 0, "data_region": "CN"}, {"contest_id": 203, "username": "wnjxyk", "user_slug": "wnjxyk", "real_name": "\u5351\u5fae\u5c0f\u5751", "country_code": "CN", "country_name": "\u4e2d\u56fd", "rank": 9, "score": 19, "finish_time": 1590894857, "global_ranking": 0, "data_region": "CN"}, {"contest_id": 203, "username": "JOHNKRAM", "user_slug": "johnkram", "real_name": "\u6c6a\u4e50\u5e73", "country_code": "", "country_name": "", "rank": 10, "score": 19, "finish_time": 1590895062, "global_ranking": 0, "data_region": "CN"}, {"contest_id": 203, "username": "tutousi", "user_slug": "tutousi", "real_name": "\u534a\u68a6\u534a\u9192\u4f34\u5fe7\u4f24", "country_code": "", "country_name": "", "rank": 11, "score": 19, "finish_time": 1590895069, "global_ranking": 0, "data_region": "CN"}, {"contest_id": 203, "username": "xh286286", "user_slug": "xh286286", "real_name": "xh286286", "country_code": "CN", "country_name": "\u4e2d\u56fd", "rank": 12, "score": 19, "finish_time": 1590895075, "global_ranking": 0, "data_region": "CN"}, {"contest_id": 203, "username": "darrenhp", "user_slug": "darrenhp", "real_name": "Darren Hp", "country_code": "", "country_name": "", "rank": 13, "score": 19, "finish_time": 1590895080, "global_ranking": 0, "data_region": "CN"}, {"contest_id": 203, "username": "lostleaf", "user_slug": "lostleaf", "real_name": "lostleaf", "country_code": "CN", "country_name": "\u4e2d\u56fd", "rank": 14, "score": 19, "finish_time": 1590895098, "global_ranking": 0, "data_region": "CN"}, {"contest_id": 203, "username": "jtjl", "user_slug": "jtjl", "real_name": "JTJL", "country_code": "", "country_name": "", "rank": 15, "score": 19, "finish_time": 1590895163, "global_ranking": 0, "data_region": "CN"}, {"contest_id": 203, "username": "dystopiawave", "user_slug": "dystopiawave", "real_name": "d y s t o p i a w a v e", "country_code": "", "country_name": "\u6d77\u5916", "rank": 16, "score": 19, "finish_time": 1590895222, "global_ranking": 0, "data_region": "CN"}, {"contest_id": 203, "username": "please_AC", "user_slug": "please_ac", "real_name": "\u72d7\u54e5\u5b87\u5b99\u6700\u5e05", "country_code": "CN", "country_name": "\u4e2d\u56fd", "rank": 17, "score": 19, "finish_time": 1590895398, "global_ranking": 0, "data_region": "CN"}, {"contest_id": 203, "username": "he-yu-am", "user_slug": "he-yu-am", "real_name": "\u4f55\u9047", "country_code": "", "country_name": "", "rank": 18, "score": 19, "finish_time": 1590895458, "global_ranking": 0, "data_region": "CN"}, {"contest_id": 203, "username": "liouzhou_101", "user_slug": "liouzhou_101", "real_name": "liouzhou_101", "country_code": "", "country_name": "", "rank": 19, "score": 19, "finish_time": 1590895471, "global_ranking": 0, "data_region": "CN"}, {"contest_id": 203, "username": "hhhyyyfff", "user_slug": "hhhyyyfff", "real_name": "hhhyyyfff", "country_code": "CN", "country_name": "\u4e2d\u56fd", "rank": 20, "score": 19, "finish_time": 1590895529, "global_ranking": 0, "data_region": "CN"}, {"contest_id": 203, "username": "ghouyl-2", "user_slug": "ghouyl-2", "real_name": "ghouyl", "country_code": "", "country_name": "", "rank": 21, "score": 19, "finish_time": 1590895738, "global_ranking": 0, "data_region": "CN"}, {"contest_id": 203, "username": "lucifer1004", "user_slug": "lucifer1004", "real_name": "lucifer1004", "country_code": "CN", "country_name": "\u4e2d\u56fd", "rank": 22, "score": 19, "finish_time": 1590895821, "global_ranking": 0, "data_region": "CN"}, {"contest_id": 203, "username": "Megumi-cs", "user_slug": "megumi-cs", "real_name": "Megumi", "country_code": "", "country_name": "", "rank": 23, "score": 19, "finish_time": 1590896034, "global_ranking": 0, "data_region": "CN"}, {"contest_id": 203, "username": "jules-megumi", "user_slug": "jules-megumi", "real_name": "Jules \u3081\u3050\u307f", "country_code": "", "country_name": "", "rank": 24, "score": 19, "finish_time": 1590896038, "global_ranking": 0, "data_region": "CN"}], "user_num": 3686}