{"time": 1589689800.1228018, "is_past": true, "submissions": [{"1560": {"id": 543548, "date": 1589682787, "question_id": 1560, "submission_id": 71375883, "status": 10, "contest_id": 197, "data_region": "CN", "fail_count": 0}, "1561": {"id": 546071, "date": 1589683284, "question_id": 1561, "submission_id": 71380139, "status": 10, "contest_id": 197, "data_region": "CN", "fail_count": 2}, "1562": {"id": 548217, "date": 1589683953, "question_id": 1562, "submission_id": 71384561, "status": 10, "contest_id": 197, "data_region": "CN", "fail_count": 0}, "1563": {"id": 549479, "date": 1589684400, "question_id": 1563, "submission_id": 71387390, "status": 10, "contest_id": 197, "data_region": "CN", "fail_count": 0}}, {"1560": {"id": 2416727, "date": 1589682651, "question_id": 1560, "submission_id": 340467651, "status": 10, "contest_id": 349, "data_region": "US", "fail_count": 0}, "1561": {"id": 2421062, "date": 1589682949, "question_id": 1561, "submission_id": 340473645, "status": 10, "contest_id": 349, "data_region": "US", "fail_count": 0}, "1562": {"id": 2424331, "date": 1589683275, "question_id": 1562, "submission_id": 340478662, "status": 10, "contest_id": 349, "data_region": "US", "fail_count": 0}, "1563": {"id": 2434839, "date": 1589684705, "question_id": 1563, "submission_id": 340497089, "status": 10, "contest_id": 349, "data_region": "US", "fail_count": 1}}, {"1560": {"id": 2417101, "date": 1589682706, "question_id": 1560, "submission_id": 340468328, "status": 10, "contest_id": 349, "data_region": "US", "fail_count": 0}, "1561": {"id": 2422028, "date": 1589683036, "question_id": 1561, "submission_id": 340475060, "status": 10, "contest_id": 349, "data_region": "US", "fail_count": 1}, "1562": {"id": 2428396, "date": 1589683739, "question_id": 1562, "submission_id": 340485314, "status": 10, "contest_id": 349, "data_region": "US", "fail_count": 0}, "1563": {"id": 2434895, "date": 1589684717, "question_id": 1563, "submission_id": 340497205, "status": 10, "contest_id": 349, "data_region": "US", "fail_count": 0}}, {"1560": {"id": 2416732, "date": 1589682657, "question_id": 1560, "submission_id": 340467686, "status": 10, "contest_id": 349, "data_region": "US", "fail_count": 0}, "1561": {"id": 2421366, "date": 1589682976, "question_id": 1561, "submission_id": 340474089, "status": 10, "contest_id": 349, "data_region": "US", "fail_count": 1}, "1562": {"id": 2426407, "date": 1589683502, "question_id": 1562, "submission_id": 340482000, "status": 10, "contest_id": 349, "data_region": "US", "fail_count": 0}, "1563": {"id": 2434894, "date": 1589684717, "question_id": 1563, "submission_id": 340497200, "status": 10, "contest_id": 349, "data_region": "US", "fail_count": 0}}, {"1560": {"id": 543790, "date": 1589682824, "question_id": 1560, "submission_id": 71376251, "status": 10, "contest_id": 197, "data_region": "CN", "fail_count": 0}, "1561": {"id": 546027, "date": 1589683273, "question_id": 1561, "submission_id": 71380060, "status": 10, "contest_id": 197, "data_region": "CN", "fail_count": 0}, "1562": {"id": 548209, "date": 1589683950, "question_id": 1562, "submission_id": 71384538, "status": 10, "contest_id": 197, "data_region": "CN", "fail_count": 0}, "1563": {"id": 550966, "date": 1589685029, "question_id": 1563, "submission_id": 71391219, "status": 10, "contest_id": 197, "data_region": "CN", "fail_count": 0}}, {"1560": {"id": 2416791, "date": 1589682675, "question_id": 1560, "submission_id": 340467838, "status": 10, "contest_id": 349, "data_region": "US", "fail_count": 0}, "1561": {"id": 2419998, "date": 1589682867, "question_id": 1561, "submission_id": 340472158, "status": 10, "contest_id": 349, "data_region": "US", "fail_count": 1}, "1562": {"id": 2423526, "date": 1589683188, "question_id": 1562, "submission_id": 340477376, "status": 10, "contest_id": 349, "data_region": "US", "fail_count": 1}, "1563": {"id": 2431432, "date": 1589684145, "question_id": 1563, "submission_id": 340490553, "status": 10, "contest_id": 349, "data_region": "US", "fail_count": 1}}, {"1560": {"id": 543060, "date": 1589682691, "question_id": 1560, "submission_id": 71375037, "status": 10, "contest_id": 197, "data_region": "CN", "fail_count": 0}, "1561": {"id": 544707, "date": 1589682953, "question_id": 1561, "submission_id": 71377636, "status": 10, "contest_id": 197, "data_region": "CN", "fail_count": 0}, "1562": {"id": 546872, "date": 1589683524, "question_id": 1562, "submission_id": 71381824, "status": 10, "contest_id": 197, "data_region": "CN", "fail_count": 1}, "1563": {"id": 550303, "date": 1589684755, "question_id": 1563, "submission_id": 71389570, "status": 10, "contest_id": 197, "data_region": "CN", "fail_count": 0}}, {"1560": {"id": 2418883, "date": 1589682803, "question_id": 1560, "submission_id": 340470681, "status": 10, "contest_id": 349, "data_region": "US", "fail_count": 0}, "1561": {"id": 2421535, "date": 1589682988, "question_id": 1561, "submission_id": 340474321, "status": 10, "contest_id": 349, "data_region": "US", "fail_count": 0}, "1562": {"id": 2429738, "date": 1589683911, "question_id": 1562, "submission_id": 340487587, "status": 10, "contest_id": 349, "data_region": "US", "fail_count": 1}, "1563": {"id": 2435124, "date": 1589684760, "question_id": 1563, "submission_id": 340497683, "status": 10, "contest_id": 349, "data_region": "US", "fail_count": 0}}, {"1560": {"id": 2416809, "date": 1589682678, "question_id": 1560, "submission_id": 340467876, "status": 10, "contest_id": 349, "data_region": "US", "fail_count": 0}, "1561": {"id": 2421644, "date": 1589682999, "question_id": 1561, "submission_id": 340474490, "status": 10, "contest_id": 349, "data_region": "US", "fail_count": 0}, "1562": {"id": 2427931, "date": 1589683681, "question_id": 1562, "submission_id": 340484504, "status": 10, "contest_id": 349, "data_region": "US", "fail_count": 0}, "1563": {"id": 2436932, "date": 1589685091, "question_id": 1563, "submission_id": 340501261, "status": 10, "contest_id": 349, "data_region": "US", "fail_count": 0}}, {"1560": {"id": 543391, "date": 1589682764, "question_id": 1560, "submission_id": 71375651, "status": 10, "contest_id": 197, "data_region": "CN", "fail_count": 0}, "1561": {"id": 545207, "date": 1589683058, "question_id": 1561, "submission_id": 71378464, "status": 10, "contest_id": 197, "data_region": "CN", "fail_count": 0}, "1562": {"id": 546840, "date": 1589683516, "question_id": 1562, "submission_id": 71381756, "status": 10, "contest_id": 197, "data_region": "CN", "fail_count": 0}, "1563": {"id": 551109, "date": 1589685092, "question_id": 1563, "submission_id": 71391605, "status": 10, "contest_id": 197, "data_region": "CN", "fail_count": 0}}, {"1560": {"id": 2426621, "date": 1589683525, "question_id": 1560, "submission_id": 340482343, "status": 10, "contest_id": 349, "data_region": "US", "fail_count": 0}, "1561": {"id": 2429292, "date": 1589683854, "question_id": 1561, "submission_id": 340486828, "status": 10, "contest_id": 349, "data_region": "US", "fail_count": 0}, "1562": {"id": 2425283, "date": 1589683379, "question_id": 1562, "submission_id": 340480198, "status": 10, "contest_id": 349, "data_region": "US", "fail_count": 0}, "1563": {"id": 2436964, "date": 1589685097, "question_id": 1563, "submission_id": 340501326, "status": 10, "contest_id": 349, "data_region": "US", "fail_count": 0}}, {"1560": {"id": 2417340, "date": 1589682721, "question_id": 1560, "submission_id": 340468666, "status": 10, "contest_id": 349, "data_region": "US", "fail_count": 0}, "1561": {"id": 2422963, "date": 1589683131, "question_id": 1561, "submission_id": 340476501, "status": 10, "contest_id": 349, "data_region": "US", "fail_count": 0}, "1562": {"id": 2425959, "date": 1589683452, "question_id": 1562, "submission_id": 340481289, "status": 10, "contest_id": 349, "data_region": "US", "fail_count": 0}, "1563": {"id": 2436980, "date": 1589685101, "question_id": 1563, "submission_id": 340501361, "status": 10, "contest_id": 349, "data_region": "US", "fail_count": 0}}, {"1560": {"id": 2416734, "date": 1589682658, "question_id": 1560, "submission_id": 340467696, "status": 10, "contest_id": 349, "data_region": "US", "fail_count": 0}, "1561": {"id": 2418431, "date": 1589682778, "question_id": 1561, "submission_id": 340470080, "status": 10, "contest_id": 349, "data_region": "US", "fail_count": 0}, "1562": {"id": 2420907, "date": 1589682937, "question_id": 1562, "submission_id": 340473423, "status": 10, "contest_id": 349, "data_region": "US", "fail_count": 0}, "1563": {"id": 2437008, "date": 1589685106, "question_id": 1563, "submission_id": 340501430, "status": 10, "contest_id": 349, "data_region": "US", "fail_count": 0}}, {"1560": {"id": 2417906, "date": 1589682752, "question_id": 1560, "submission_id": 340469402, "status": 10, "contest_id": 349, "data_region": "US", "fail_count": 0}, "1561": {"id": 2422543, "date": 1589683088, "question_id": 1561, "submission_id": 340475837, "status": 10, "contest_id": 349, "data_region": "US", "fail_count": 0}, "1562": {"id": 2427272, "date": 1589683600, "question_id": 1562, "submission_id": 340483408, "status": 10, "contest_id": 349, "data_region": "US", "fail_count": 0}, "1563": {"id": 2437208, "date": 1589685146, "question_id": 1563, "submission_id": 340501828, "status": 10, "contest_id": 349, "data_region": "US", "fail_count": 0}}, {"1560": {"id": 2417252, "date": 1589682716, "question_id": 1560, "submission_id": 340468550, "status": 10, "contest_id": 349, "data_region": "US", "fail_count": 0}, "1561": {"id": 2426302, "date": 1589683491, "question_id": 1561, "submission_id": 340481837, "status": 10, "contest_id": 349, "data_region": "US", "fail_count": 1}, "1562": {"id": 2427982, "date": 1589683689, "question_id": 1562, "submission_id": 340484604, "status": 10, "contest_id": 349, "data_region": "US", "fail_count": 0}, "1563": {"id": 2434101, "date": 1589684574, "question_id": 1563, "submission_id": 340495660, "status": 10, "contest_id": 349, "data_region": "US", "fail_count": 1}}, {"1560": {"id": 2417203, "date": 1589682713, "question_id": 1560, "submission_id": 340468485, "status": 10, "contest_id": 349, "data_region": "US", "fail_count": 0}, "1561": {"id": 2422162, "date": 1589683050, "question_id": 1561, "submission_id": 340475249, "status": 10, "contest_id": 349, "data_region": "US", "fail_count": 0}, "1562": {"id": 2424949, "date": 1589683344, "question_id": 1562, "submission_id": 340479652, "status": 10, "contest_id": 349, "data_region": "US", "fail_count": 0}, "1563": {"id": 2437374, "date": 1589685176, "question_id": 1563, "submission_id": 340502169, "status": 10, "contest_id": 349, "data_region": "US", "fail_count": 0}}, {"1560": {"id": 2417734, "date": 1589682743, "question_id": 1560, "submission_id": 340469180, "status": 10, "contest_id": 349, "data_region": "US", "fail_count": 0}, "1561": {"id": 2421289, "date": 1589682969, "question_id": 1561, "submission_id": 340473977, "status": 10, "contest_id": 349, "data_region": "US", "fail_count": 0}, "1562": {"id": 2437377, "date": 1589685177, "question_id": 1562, "submission_id": 340502172, "status": 10, "contest_id": 349, "data_region": "US", "fail_count": 0}, "1563": {"id": 2431649, "date": 1589684178, "question_id": 1563, "submission_id": 340490950, "status": 10, "contest_id": 349, "data_region": "US", "fail_count": 0}}, {"1560": {"id": 545126, "date": 1589683039, "question_id": 1560, "submission_id": 71378334, "status": 10, "contest_id": 197, "data_region": "CN", "fail_count": 0}, "1561": {"id": 545558, "date": 1589683148, "question_id": 1561, "submission_id": 71379151, "status": 10, "contest_id": 197, "data_region": "CN", "fail_count": 0}, "1562": {"id": 546880, "date": 1589683526, "question_id": 1562, "submission_id": 71381836, "status": 10, "contest_id": 197, "data_region": "CN", "fail_count": 0}, "1563": {"id": 551283, "date": 1589685179, "question_id": 1563, "submission_id": 71392063, "status": 10, "contest_id": 197, "data_region": "CN", "fail_count": 0}}, {"1560": {"id": 2416826, "date": 1589682680, "question_id": 1560, "submission_id": 340467904, "status": 10, "contest_id": 349, "data_region": "US", "fail_count": 0}, "1561": {"id": 2420686, "date": 1589682917, "question_id": 1561, "submission_id": 340473092, "status": 10, "contest_id": 349, "data_region": "US", "fail_count": 0}, "1562": {"id": 2422820, "date": 1589683117, "question_id": 1562, "submission_id": 340476281, "status": 10, "contest_id": 349, "data_region": "US", "fail_count": 0}, "1563": {"id": 2435820, "date": 1589684885, "question_id": 1563, "submission_id": 340499024, "status": 10, "contest_id": 349, "data_region": "US", "fail_count": 1}}, {"1560": {"id": 2430513, "date": 1589684015, "question_id": 1560, "submission_id": 340488948, "status": 10, "contest_id": 349, "data_region": "US", "fail_count": 0}, "1561": {"id": 2433013, "date": 1589684393, "question_id": 1561, "submission_id": 340493535, "status": 10, "contest_id": 349, "data_region": "US", "fail_count": 0}, "1562": {"id": 2437430, "date": 1589685186, "question_id": 1562, "submission_id": 340502268, "status": 10, "contest_id": 349, "data_region": "US", "fail_count": 0}, "1563": {"id": 2428433, "date": 1589683745, "question_id": 1563, "submission_id": 340485388, "status": 10, "contest_id": 349, "data_region": "US", "fail_count": 0}}, {"1560": {"id": 2417016, "date": 1589682699, "question_id": 1560, "submission_id": 340468210, "status": 10, "contest_id": 349, "data_region": "US", "fail_count": 0}, "1561": {"id": 2421671, "date": 1589683001, "question_id": 1561, "submission_id": 340474529, "status": 10, "contest_id": 349, "data_region": "US", "fail_count": 0}, "1562": {"id": 2429756, "date": 1589683913, "question_id": 1562, "submission_id": 340487624, "status": 10, "contest_id": 349, "data_region": "US", "fail_count": 0}, "1563": {"id": 2437538, "date": 1589685208, "question_id": 1563, "submission_id": 340502504, "status": 10, "contest_id": 349, "data_region": "US", "fail_count": 0}}, {"1560": {"id": 2416933, "date": 1589682693, "question_id": 1560, "submission_id": 340468082, "status": 10, "contest_id": 349, "data_region": "US", "fail_count": 0}, "1561": {"id": 2420715, "date": 1589682919, "question_id": 1561, "submission_id": 340473127, "status": 10, "contest_id": 349, "data_region": "US", "fail_count": 0}, "1562": {"id": 2427203, "date": 1589683593, "question_id": 1562, "submission_id": 340483303, "status": 10, "contest_id": 349, "data_region": "US", "fail_count": 0}, "1563": {"id": 2436001, "date": 1589684919, "question_id": 1563, "submission_id": 340499396, "status": 10, "contest_id": 349, "data_region": "US", "fail_count": 1}}, {"1560": {"id": 543089, "date": 1589682703, "question_id": 1560, "submission_id": 71375113, "status": 10, "contest_id": 197, "data_region": "CN", "fail_count": 0}, "1561": {"id": 544491, "date": 1589682918, "question_id": 1561, "submission_id": 71377287, "status": 10, "contest_id": 197, "data_region": "CN", "fail_count": 0}, "1562": {"id": 547672, "date": 1589683766, "question_id": 1562, "submission_id": 71383367, "status": 10, "contest_id": 197, "data_region": "CN", "fail_count": 2}, "1563": {"id": 550002, "date": 1589684620, "question_id": 1563, "submission_id": 71388748, "status": 10, "contest_id": 197, "data_region": "CN", "fail_count": 0}}, {"1560": {"id": 2419697, "date": 1589682849, "question_id": 1560, "submission_id": 340471748, "status": 10, "contest_id": 349, "data_region": "US", "fail_count": 0}, "1561": {"id": 2422113, "date": 1589683045, "question_id": 1561, "submission_id": 340475179, "status": 10, "contest_id": 349, "data_region": "US", "fail_count": 0}, "1562": {"id": 2429652, "date": 1589683898, "question_id": 1562, "submission_id": 340487427, "status": 10, "contest_id": 349, "data_region": "US", "fail_count": 0}, "1563": {"id": 2436028, "date": 1589684924, "question_id": 1563, "submission_id": 340499453, "status": 10, "contest_id": 349, "data_region": "US", "fail_count": 1}}, {"1560": {"id": 2416899, "date": 1589682689, "question_id": 1560, "submission_id": 340468030, "status": 10, "contest_id": 349, "data_region": "US", "fail_count": 0}, "1561": {"id": 2421308, "date": 1589682971, "question_id": 1561, "submission_id": 340474003, "status": 10, "contest_id": 349, "data_region": "US", "fail_count": 1}, "1562": {"id": 2426237, "date": 1589683483, "question_id": 1562, "submission_id": 340481737, "status": 10, "contest_id": 349, "data_region": "US", "fail_count": 0}, "1563": {"id": 2436078, "date": 1589684933, "question_id": 1563, "submission_id": 340499548, "status": 10, "contest_id": 349, "data_region": "US", "fail_count": 0}}], "questions": [{"id": 1394, "question_id": 1560, "credit": 3, "title": "Number of Students Doing Homework at a Given Time", "title_slug": "number-of-students-doing-homework-at-a-given-time"}, {"id": 1395, "question_id": 1561, "credit": 4, "title": "Rearrange Words in a Sentence", "title_slug": "rearrange-words-in-a-sentence"}, {"id": 1396, "question_id": 1562, "credit": 5, "title": "People Whose List of Favorite Companies Is Not a Subset of Another List", "title_slug": "people-whose-list-of-favorite-companies-is-not-a-subset-of-another-list"}, {"id": 1397, "question_id": 1563, "credit": 7, "title": "Maximum Number of Darts Inside of a Circular Dartboard", "title_slug": "maximum-number-of-darts-inside-of-a-circular-dartboard"}], "total_rank": [{"contest_id": 197, "username": "Megumi-cs", "user_slug": "megumi-cs", "country_code": "", "country_name": null, "rank": 51, "score": 19, "finish_time": 1589685000, "global_ranking": 0, "data_region": "CN"}, {"contest_id": 349, "username": "zcgzcgzcg", "user_slug": "zcgzcgzcg", "country_code": "", "country_name": null, "rank": 52, "score": 19, "finish_time": 1589685005, "global_ranking": 0, "data_region": "US"}, {"contest_id": 349, "username": "hwhf6699", "user_slug": "hwhf6699", "country_code": "", "country_name": null, "rank": 53, "score": 19, "finish_time": 1589685017, "global_ranking": 0, "data_region": "US"}, {"contest_id": 349, "username": "yubowenok", "user_slug": "yubowenok", "country_code": "CN", "country_name": "China", "rank": 54, "score": 19, "finish_time": 1589685017, "global_ranking": 0, "data_region": "US"}, {"contest_id": 197, "username": "YusenZhang_chatc", "user_slug": "yusenzhang_chatc", "country_code": "", "country_name": null, "rank": 55, "score": 19, "finish_time": 1589685029, "global_ranking": 0, "data_region": "CN"}, {"contest_id": 349, "username": "kzyKT", "user_slug": "kzykt", "country_code": "JP", "country_name": "Japan", "rank": 56, "score": 19, "finish_time": 1589685045, "global_ranking": 0, "data_region": "US"}, {"contest_id": 197, "username": "Heltion", "user_slug": "heltion", "country_code": "", "country_name": null, "rank": 57, "score": 19, "finish_time": 1589685055, "global_ranking": 0, "data_region": "CN"}, {"contest_id": 349, "username": "mirosuaf", "user_slug": "mirosuaf", "country_code": "", "country_name": null, "rank": 58, "score": 19, "finish_time": 1589685060, "global_ranking": 0, "data_region": "US"}, {"contest_id": 349, "username": "nguyenngochuy91", "user_slug": "nguyenngochuy91", "country_code": "VN", "country_name": "Vietnam", "rank": 59, "score": 19, "finish_time": 1589685091, "global_ranking": 0, "data_region": "US"}, {"contest_id": 197, "username": "CE_RE_WAyitiaolong", "user_slug": "ce_re_wayitiaolong", "country_code": "", "country_name": null, "rank": 60, "score": 19, "finish_time": 1589685092, "global_ranking": 0, "data_region": "CN"}, {"contest_id": 349, "username": "kotomord", "user_slug": "kotomord", "country_code": "", "country_name": null, "rank": 61, "score": 19, "finish_time": 1589685097, "global_ranking": 0, "data_region": "US"}, {"contest_id": 349, "username": "zhantons", "user_slug": "zhantons", "country_code": "", "country_name": null, "rank": 62, "score": 19, "finish_time": 1589685101, "global_ranking": 0, "data_region": "US"}, {"contest_id": 349, "username": "onakasuitacity", "user_slug": "onakasuitacity", "country_code": "JP", "country_name": "Japan", "rank": 63, "score": 19, "finish_time": 1589685106, "global_ranking": 0, "data_region": "US"}, {"contest_id": 349, "username": "kai-chieh", "user_slug": "kai-chieh", "country_code": "TW", "country_name": "Taiwan", "rank": 64, "score": 19, "finish_time": 1589685146, "global_ranking": 0, "data_region": "US"}, {"contest_id": 349, "username": "Dshawn", "user_slug": "dshawn", "country_code": "CN", "country_name": "China", "rank": 65, "score": 19, "finish_time": 1589685174, "global_ranking": 0, "data_region": "US"}, {"contest_id": 349, "username": "nskybytskyi", "user_slug": "nskybytskyi", "country_code": "UA", "country_name": "Ukraine", "rank": 66, "score": 19, "finish_time": 1589685176, "global_ranking": 0, "data_region": "US"}, {"contest_id": 349, "username": "0am", "user_slug": "0am", "country_code": "CA", "country_name": "Canada", "rank": 67, "score": 19, "finish_time": 1589685177, "global_ranking": 0, "data_region": "US"}, {"contest_id": 197, "username": "zesen", "user_slug": "zesen", "country_code": "", "country_name": null, "rank": 68, "score": 19, "finish_time": 1589685179, "global_ranking": 0, "data_region": "CN"}, {"contest_id": 349, "username": "sshang", "user_slug": "sshang", "country_code": "CN", "country_name": "China", "rank": 69, "score": 19, "finish_time": 1589685185, "global_ranking": 0, "data_region": "US"}, {"contest_id": 349, "username": "damaoge", "user_slug": "damaoge", "country_code": "CN", "country_name": "China", "rank": 70, "score": 19, "finish_time": 1589685186, "global_ranking": 0, "data_region": "US"}, {"contest_id": 349, "username": "ShidaLei", "user_slug": "shidalei", "country_code": "JP", "country_name": "Japan", "rank": 71, "score": 19, "finish_time": 1589685208, "global_ranking": 0, "data_region": "US"}, {"contest_id": 349, "username": "kasperyhr", "user_slug": "kasperyhr", "country_code": "US", "country_name": "United States", "rank": 72, "score": 19, "finish_time": 1589685219, "global_ranking": 0, "data_region": "US"}, {"contest_id": 197, "username": "lucifer1004", "user_slug": "lucifer1004", "country_code": "", "country_name": null, "rank": 73, "score": 19, "finish_time": 1589685220, "global_ranking": 0, "data_region": "CN"}, {"contest_id": 349, "username": "pze168", "user_slug": "pze168", "country_code": "US", "country_name": "United States", "rank": 74, "score": 19, "finish_time": 1589685224, "global_ranking": 0, "data_region": "US"}, {"contest_id": 349, "username": "tylerwang", "user_slug": "tylerwang", "country_code": "US", "country_name": "United States", "rank": 75, "score": 19, "finish_time": 1589685233, "global_ranking": 0, "data_region": "US"}], "user_num": 13036}